{"2064647391":["Vesteria.lua"],"4789838965":["Vesteria.lua"],"2260598172":["Vesteria.lua"],"3528530753":["Vesteria.lua"],"2119298605":["Vesteria.lua"],"4282412540":["Vesteria.lua"],"5516563563":["Vesteria.lua"],"4544425669":["Vesteria.lua"],"3323943158":["Vesteria.lua"],"5352389410":["Vesteria.lua"],"3372071669":["Vesteria.lua"],"2496503573":["Vesteria.lua"],"5352390681":["Vesteria.lua"],"4920153409":["Vesteria.lua"],"3232938614":["Vesteria.lua"],"2544075708":["Vesteria.lua"],"2573917748":["Vesteria.lua"],"5352028694":["Vesteria.lua"],"4409709778":["Vesteria.lua"],"3303140173":["Vesteria.lua"],"5352395552":["Vesteria.lua"],"3330001318":["Vesteria.lua"],"2878620739":["Vesteria.lua"],"2471035818":["Vesteria.lua"],"5352392098":["Vesteria.lua"],"3852057184":["Vesteria.lua"],"2376885433":["Vesteria.lua"],"3112029149":["Vesteria.lua"],"5367595219":["Vesteria.lua"],"2093766642":["Vesteria.lua"],"2546689567":["Vesteria.lua"],"2677014001":["Vesteria.lua"],"3232913902":["Vesteria.lua"],"2035250551":["Vesteria.lua"],"5986816252":["Vesteria.lua"],"5367884422":["Vesteria.lua"],"2470481225":["Vesteria.lua"],"5718871146":["Vesteria.lua"],"2061558182":["Vesteria.lua"],"1458767429":["ABACoinfarm.lua"],"4653017449":["Vesteria.lua"],"6652312122":["Vesteria.lua"],"3806133797":["Vesteria.lua"],"2535681150":["Vesteria.lua"],"6569748638":["Vesteria.lua"],"5220944559":["Vesteria.lua"],"3460262616":["Vesteria.lua"],"2060360203":["Vesteria.lua"],"5995061312":["Vesteria.lua"],"2060556572":["Vesteria.lua"],"3273679677":["Vesteria.lua"],"3360349837":["Vesteria.lua"],"4837338537":["Vesteria.lua"],"2180867434":["Vesteria.lua"],"4623219432":["Vesteria.lua"],"4561988219":["Vesteria.lua"],"2376890690":["Vesteria.lua"],"5352391313":["Vesteria.lua"],"3207211233":["Vesteria.lua"],"5574247235":["Vesteria.lua"],"3806158069":["Vesteria.lua"]}